README.rst
setup.py
HTS_waterworks.egg-info/PKG-INFO
HTS_waterworks.egg-info/SOURCES.txt
HTS_waterworks.egg-info/dependency_links.txt
HTS_waterworks.egg-info/requires.txt
HTS_waterworks.egg-info/top_level.txt
hts_waterworks/__init__.py
hts_waterworks/annotation.py
hts_waterworks/bootstrap.py
hts_waterworks/call_peaks.py
hts_waterworks/clip_seq.py
hts_waterworks/mapping.py
hts_waterworks/motif_discovery.py
hts_waterworks/pas_seq.py
hts_waterworks/preprocessing.py
hts_waterworks/visualize.py