Metadata-Version: 1.1
Name: HTS-waterworks
Version: 0.1
Summary: A python pipeline for analyzing high-throughput sequencing data
Home-page: http://github.com/jakebiesinger/HTS-waterworks
Author: Jacob Biesinger
Author-email: jake.biesinger@gmail.com
License: MIT
Keywords: pipeline parallel bioinformatics science
Platform: UNKNOWN
Classifier: Intended Audience :: End Users/Desktop
Classifier: Intended Audience :: Developers
Classifier: Intended Audience :: Science/Research
Classifier: Intended Audience :: Information Technology
Classifier: License :: OSI Approved :: MIT License
Classifier: Programming Language :: Python
Classifier: Topic :: Scientific/Engineering
Classifier: Topic :: Scientific/Engineering :: Bio-Informatics
Classifier: Topic :: System :: Distributed Computing
Classifier: Topic :: Software Development :: Build Tools
Classifier: Topic :: Software Development :: Build Tools
Classifier: Topic :: Software Development :: Libraries
Classifier: Environment :: Console
